beogym/Equirec2Perspec.py
beogym/Equirec2Perspec_cpu.py
beogym/Zero.py
beogym/__init__.py
beogym/agent.py
beogym/beogym.py
beogym/config.py
beogym/customppo.py
beogym/data_helper.py
beogym/dynamic_plot.py
beogym/fixrillb.py
beogym/go.py
beogym/graphTransfer.py
beogym/gymray.py
beogym/gymray2.py
beogym/seperate.py
beogym/test.py
beogym/tg.py
beogym/tta.py
beogym-0.0.5.dist-info/METADATA
beogym-0.0.5.dist-info/WHEEL
beogym-0.0.5.dist-info/top_level.txt
beogym-0.0.5.dist-info/RECORD
